{
  "autoRetry": null,
  "browser": null,
  "dataSource": null,
  "disableVisuals": null,
  "disallowInsecureCertificates": null,
  "failOnJavaScriptError": null,
  "filters": [],
  "finalDelay": null,
  "globalStepDelay": null,
  "httpHeaders": [],
  "importOnly": false,
  "language": null,
  "links": [],
  "maxAjaxDelay": null,
  "maxConcurrentDataRows": null,
  "maxWaitDelay": null,
  "name": "03 - US - Place Order - New User - Backend",
  "notifications": null,
  "publicStatusEnabled": false,
  "region": null,
  "screenshotCompareEnabled": false,
  "screenshotCompareThreshold": 0.1,
  "startUrl": "",
  "steps": [
    {
      "command": "open",
      "condition": null,
      "optional": false,
      "private": false,
      "sequence": 0,
      "target": "",
      "value": "{{startUrl}}wp-admin",
      "variableName": ""
    },
    {
      "command": "execute",
      "condition": null,
      "optional": false,
      "private": false,
      "sequence": 1,
      "target": "",
      "value": "64766b920bf912e0780e2f58",
      "variableName": ""
    },
    {
      "command": "mouseOver",
      "condition": null,
      "optional": false,
      "private": false,
      "sequence": 2,
      "target": "a[href=\"admin.php?page=wc-admin\"] > .wp-menu-name",
      "value": "",
      "variableName": ""
    },
    {
      "command": "click",
      "condition": null,
      "optional": false,
      "private": false,
      "sequence": 3,
      "target": [
        {
          "selector": "a[href=\"edit.php?post_type=shop_order\"]"
        },
        {
          "selector": "a[href=\"admin.php?page=wc-orders\"]"
        }
      ]
    },
    {
      "command": "assertText",
      "condition": null,
      "optional": false,
      "private": false,
      "sequence": 4,
      "target": [
        {
          "selector": "tr#order-{{orderNumber}} > td.order_total.column-order_total > .tips > .woocommerce-Price-amount.amount"
        },
        {
          "selector": "tr#post-{{orderNumber}} > td.order_total.column-order_total > .tips > .woocommerce-Price-amount.amount"
        }
      ],
      "value": "{{total}}",
      "variableName": ""
    },
    {
      "command": "click",
      "condition": null,
      "optional": false,
      "private": false,
      "sequence": 5,
      "target": [
        {
          "selector": "a[href*=\"/wp-admin/post.php?post={{orderNumber}}&action=edit\"] > strong"
        },
        {
          "selector": "a[href*=\"/wp-admin/admin.php?page=wc-orders&action=edit&id={{orderNumber}}\"] > strong"
        }
      ]
    },
    {
      "command": "assertTextPresent",
      "condition": null,
      "optional": false,
      "private": false,
      "sequence": 6,
      "target": ".woocommerce-order-data__meta",
      "value": "Credit / Debit Card",
      "variableName": ""
    },
    {
      "command": "assertTextPresent",
      "condition": null,
      "optional": false,
      "private": false,
      "sequence": 7,
      "target": "#select2-order_status-container",
      "value": "Processing"
    },
    {
      "command": "assertText",
      "condition": null,
      "optional": false,
      "private": false,
      "sequence": 8,
      "target": "div.order_data_column:nth-of-type(2) > .address > p:nth-of-type(1)",
      "value": "{{firstName}} {{lastName}}\n{{company}}\n{{street}}\n{{city}}, {{state}} {{zipCode}}\n{{countryComplete}}",
      "variableName": ""
    },
    {
      "command": "assertText",
      "condition": null,
      "optional": false,
      "private": false,
      "sequence": 9,
      "target": "a[href*=\"mailto:qa+gi_order_\"]",
      "value": "{{email}}",
      "variableName": ""
    },
    {
      "command": "assertText",
      "condition": null,
      "optional": false,
      "private": false,
      "sequence": 10,
      "target": "div.order_data_column:nth-of-type(2) > .address a[href*=\"tel:\"]",
      "value": "{{phone}}",
      "variableName": ""
    },
    {
      "command": "assertText",
      "condition": null,
      "optional": false,
      "private": false,
      "sequence": 11,
      "target": "div.order_data_column:nth-of-type(3) > .address > p:nth-of-type(1)",
      "value": "{{firstName}} {{lastName2}}\n{{company2}}\n{{street3}}\n{{city}}, {{state}} {{zipCode}}\n{{countryComplete}}",
      "variableName": ""
    },
    {
      "command": "assertTextPresent",
      "condition": null,
      "optional": false,
      "private": false,
      "sequence": 12,
      "target": "a[href*=\"/wp-admin/post.php?post=\"]",
      "value": "{{prod_desc}}"
    },
    {
      "command": "assertText",
      "condition": null,
      "optional": false,
      "private": false,
      "sequence": 13,
      "target": "td.item_cost > .view > .woocommerce-Price-amount.amount > bdi",
      "value": "{{unitPrice}}",
      "variableName": ""
    },
    {
      "command": "assertText",
      "condition": null,
      "optional": false,
      "private": false,
      "sequence": 14,
      "target": "tr.shipping > td.line_cost > .view > .woocommerce-Price-amount.amount",
      "value": "{{shippingPrice}}",
      "variableName": ""
    },
    {
      "command": "assertText",
      "condition": null,
      "optional": false,
      "private": false,
      "sequence": 15,
      "target": "table.wc-order-totals:nth-of-type(1) > tbody > tr:nth-of-type(1) > td.total > .woocommerce-Price-amount.amount > bdi",
      "value": "{{subtotalPrice}}",
      "variableName": ""
    },
    {
      "command": "assertText",
      "condition": null,
      "optional": false,
      "private": false,
      "sequence": 16,
      "target": ".wc-order-data-row.wc-order-totals-items > table.wc-order-totals:nth-of-type(1) > tbody > tr:nth-of-type(2) > td.total > .woocommerce-Price-amount.amount > bdi",
      "value": "{{shippingPrice}}",
      "variableName": ""
    },
    {
      "command": "assertText",
      "condition": null,
      "optional": false,
      "private": false,
      "sequence": 17,
      "target": ".wc-order-data-row.wc-order-totals-items > table.wc-order-totals:nth-of-type(1) > tbody > tr:nth-of-type(3) > td.total > .woocommerce-Price-amount.amount > bdi",
      "value": "{{total}}",
      "variableName": ""
    },
    {
      "command": "assertText",
      "condition": null,
      "optional": false,
      "private": false,
      "sequence": 18,
      "target": "table.wc-order-totals:nth-of-type(2) > tbody > tr:nth-of-type(1) > td.total > .woocommerce-Price-amount.amount > bdi",
      "value": "{{total}}",
      "variableName": ""
    },
    {
      "command": "assertElementPresent",
      "condition": null,
      "optional": true,
      "private": false,
      "sequence": 19,
      "target": "a[href*=\"/wp-admin/admin-ajax.php?action=generate_wpo_wcpdf&document_type=invoice&order_ids={{orderNumber}}&access_key=wc_order_\"]",
      "value": "",
      "variableName": ""
    },
    {
      "command": "assertEval",
      "condition": null,
      "optional": false,
      "private": false,
      "sequence": 20,
      "target": "",
      "value": "function checkAdminNote(note) {\n    const pattern = /Stripe charge complete \\(Charge ID: ch_[a-zA-Z0-9]+\\)/;\n    return pattern.test(note);\n}\n\nlet note = document.querySelector('ul.order_notes > li:nth-of-type(1) > div > p').textContent\n\nreturn checkAdminNote(note)\n",
      "variableName": ""
    }
  ],
  "testFrequency": 0,
  "testFrequencyAdvanced": [],
  "viewportSize": null,
  "_gi": {
    "testId": "67c9add9c4f6da836c3a94a4",
    "suiteId": "67c09815c4c19f03ef9fe1f5",
    "suiteName": "US - Place Order"
  }
}