{
  "autoRetry": null,
  "browser": null,
  "dataSource": null,
  "disableVisuals": null,
  "disallowInsecureCertificates": null,
  "failOnJavaScriptError": null,
  "filters": [],
  "finalDelay": null,
  "globalStepDelay": null,
  "httpHeaders": [],
  "importOnly": true,
  "language": null,
  "links": [],
  "maxAjaxDelay": null,
  "maxConcurrentDataRows": null,
  "maxWaitDelay": null,
  "name": "Place Order - New User - Renew",
  "notifications": null,
  "publicStatusEnabled": false,
  "region": null,
  "screenshotCompareEnabled": false,
  "screenshotCompareThreshold": 0.1,
  "startUrl": "",
  "steps": [
    {
      "command": "open",
      "condition": null,
      "optional": false,
      "private": false,
      "sequence": 0,
      "target": "",
      "value": "{{startUrl}}wp-admin",
      "variableName": ""
    },
    {
      "command": "execute",
      "condition": null,
      "optional": false,
      "private": false,
      "sequence": 1,
      "target": "",
      "value": "68c17db15081f036c98acf80",
      "variableName": ""
    },
    {
      "command": "click",
      "condition": null,
      "optional": false,
      "private": false,
      "sequence": 2,
      "target": "a[href=\"admin.php?page=wc-admin\"] > .wp-menu-name",
      "value": "",
      "variableName": ""
    },
    {
      "command": "execute",
      "condition": null,
      "optional": false,
      "private": false,
      "sequence": 3,
      "target": "",
      "value": "6022b6b2d2fb38677e5d8a9a",
      "variableName": ""
    },
    {
      "command": "click",
      "condition": null,
      "optional": false,
      "private": false,
      "sequence": 4,
      "target": "a[href=\"admin.php?page=wc-orders--shop_subscription\"]"
    },
    {
      "command": "execute",
      "condition": null,
      "optional": false,
      "private": false,
      "sequence": 5,
      "target": "",
      "value": "6022b6b2d2fb38677e5d8a9a",
      "variableName": ""
    },
    {
      "command": "click",
      "condition": null,
      "optional": false,
      "private": false,
      "sequence": 6,
      "target": "a[href*=\"admin.php?page=wc-orders--shop_subscription&action=edit&id={{subscriptionNumber}}\"] > strong"
    },
    {
      "command": "execute",
      "condition": null,
      "optional": false,
      "private": false,
      "sequence": 7,
      "target": "",
      "value": "6022b6b2d2fb38677e5d8a9a",
      "variableName": ""
    },
    {
      "command": "click",
      "condition": null,
      "optional": false,
      "private": false,
      "sequence": 8,
      "target": "select[name=\"wc_order_action\"]",
      "value": null
    },
    {
      "command": "assign",
      "condition": null,
      "optional": false,
      "private": false,
      "sequence": 9,
      "target": "select[name=\"wc_order_action\"]",
      "value": "wcs_process_renewal"
    },
    {
      "command": "click",
      "condition": null,
      "optional": false,
      "private": false,
      "sequence": 10,
      "target": "button[name=\"save\"]",
      "value": null
    },
    {
      "command": "assertElementPresent",
      "condition": null,
      "optional": false,
      "private": false,
      "sequence": 11,
      "target": "tr:nth-of-type(1) > td:nth-of-type(5) > .amount > .woocommerce-Price-amount.amount",
      "value": ""
    },
    {
      "command": "click",
      "condition": null,
      "optional": false,
      "private": false,
      "sequence": 12,
      "target": "tr:nth-of-type(1) a[href*=\"/wp-admin/admin.php?page=wc-orders&action=edit&id=\"][aria-label*=\"Edit order number\"]"
    }
  ],
  "testFrequency": 0,
  "testFrequencyAdvanced": [],
  "viewportSize": null,
  "_gi": {
    "testId": "68c2af025081f036c9baec67",
    "suiteId": "68c16e5b5081f036c9877178",
    "suiteName": "Gruum - Common steps"
  }
}