{
  "autoRetry": null,
  "browser": null,
  "browserVersion": "Mozilla/5.0 (Macintosh; Intel Mac OS X 10_15_7) AppleWebKit/537.36 (KHTML, like Gecko) Chrome/100.0.4896.127 Safari/537.36",
  "dataSource": null,
  "disableVisuals": null,
  "disallowInsecureCertificates": null,
  "extensionVersion": "6.1.0",
  "failOnJavaScriptError": null,
  "filters": [],
  "finalDelay": null,
  "globalStepDelay": null,
  "httpHeaders": [],
  "importOnly": true,
  "language": null,
  "links": [],
  "maxAjaxDelay": null,
  "maxConcurrentDataRows": null,
  "maxWaitDelay": null,
  "name": "Fill Checkout",
  "notifications": null,
  "publicStatusEnabled": false,
  "region": null,
  "screenshotCompareEnabled": null,
  "screenshotCompareThreshold": 0.1,
  "startUrl": "",
  "steps": [
    {
      "command": "click",
      "condition": {
        "statement": "const element = document.querySelector('#ship-to-different-address-checkbox').checked\n\nreturn !element && '{{logged}}' !== 'yes'"
      },
      "optional": false,
      "private": false,
      "sequence": 0,
      "target": "#ship-to-different-address-checkbox",
      "value": "",
      "variableName": ""
    },
    {
      "command": "assign",
      "condition": {
        "statement": "return '{{logged}}' !== 'yes'"
      },
      "optional": false,
      "private": false,
      "sequence": 1,
      "target": "#billing_first_name",
      "value": "{{firstName}}",
      "variableName": ""
    },
    {
      "command": "assign",
      "condition": {
        "statement": "return '{{logged}}' !== 'yes'"
      },
      "optional": false,
      "private": false,
      "sequence": 2,
      "target": "#billing_last_name",
      "value": "{{lastName}}",
      "variableName": ""
    },
    {
      "command": "assign",
      "condition": {
        "statement": "return '{{logged}}' !== 'yes'"
      },
      "optional": false,
      "private": false,
      "sequence": 3,
      "target": "#billing_company",
      "value": "{{company}}",
      "variableName": ""
    },
    {
      "command": "click",
      "condition": {
        "statement": "return '{{logged}}' !== 'yes'"
      },
      "optional": false,
      "private": false,
      "sequence": 4,
      "target": "#billing_country",
      "value": "",
      "variableName": ""
    },
    {
      "command": "click",
      "condition": {
        "statement": "return '{{logged}}' !== 'yes'"
      },
      "optional": false,
      "private": false,
      "sequence": 5,
      "target": "#billing_country > option[value=\"{{country}}\"]",
      "value": "",
      "variableName": ""
    },
    {
      "command": "assign",
      "condition": {
        "statement": "return '{{logged}}' !== 'yes'"
      },
      "optional": false,
      "private": false,
      "sequence": 6,
      "target": "#billing_address_1",
      "value": "{{street}}",
      "variableName": ""
    },
    {
      "command": "assign",
      "condition": {
        "statement": "return '{{logged}}' !== 'yes'"
      },
      "optional": false,
      "private": false,
      "sequence": 7,
      "target": "#billing_address_2",
      "value": "{{street2}}",
      "variableName": ""
    },
    {
      "command": "assign",
      "condition": {
        "statement": "return '{{logged}}' !== 'yes'"
      },
      "optional": false,
      "private": false,
      "sequence": 8,
      "target": "#billing_city",
      "value": "{{city}}",
      "variableName": ""
    },
    {
      "command": "click",
      "condition": {
        "statement": "return '{{logged}}' !== 'yes'"
      },
      "optional": false,
      "private": false,
      "sequence": 9,
      "target": "#billing_state",
      "value": "",
      "variableName": ""
    },
    {
      "command": "click",
      "condition": {
        "statement": "return '{{logged}}' !== 'yes'"
      },
      "optional": false,
      "private": false,
      "sequence": 10,
      "target": "#billing_state > option[value=\"{{state}}\"]",
      "value": "",
      "variableName": ""
    },
    {
      "command": "assign",
      "condition": {
        "statement": "return '{{logged}}' !== 'yes'"
      },
      "optional": false,
      "private": false,
      "sequence": 11,
      "target": "#billing_postcode",
      "value": "{{zipCode}}",
      "variableName": ""
    },
    {
      "command": "assign",
      "condition": {
        "statement": "return '{{logged}}' !== 'yes'"
      },
      "optional": false,
      "private": false,
      "sequence": 12,
      "target": "#billing_phone",
      "value": "{{phone}}",
      "variableName": ""
    },
    {
      "command": "assign",
      "condition": {
        "statement": "return '{{logged}}' !== 'yes'"
      },
      "optional": false,
      "private": false,
      "sequence": 13,
      "target": "#billing_email",
      "value": "{{email}}",
      "variableName": ""
    },
    {
      "command": "click",
      "condition": {
        "statement": "const element = document.querySelector('#mailchimp_woocommerce_newsletter')\n\nreturn element.checked"
      },
      "optional": false,
      "private": false,
      "sequence": 14,
      "target": "#mailchimp_woocommerce_newsletter",
      "value": ""
    },
    {
      "command": "click",
      "condition": {
        "statement": "return '{{logged}}' !== 'yes'"
      },
      "optional": false,
      "private": false,
      "sequence": 15,
      "target": "#createaccount",
      "value": "",
      "variableName": ""
    },
    {
      "command": "assign",
      "condition": {
        "statement": "return '{{logged}}' !== 'yes'"
      },
      "optional": false,
      "private": false,
      "sequence": 16,
      "target": "#shipping_first_name",
      "value": "{{firstName}}",
      "variableName": ""
    },
    {
      "command": "assign",
      "condition": {
        "statement": "return '{{logged}}' !== 'yes'"
      },
      "optional": false,
      "private": false,
      "sequence": 17,
      "target": "#shipping_last_name",
      "value": "{{lastName2}}",
      "variableName": ""
    },
    {
      "command": "assign",
      "condition": {
        "statement": "return '{{logged}}' !== 'yes'"
      },
      "optional": false,
      "private": false,
      "sequence": 18,
      "target": "#shipping_company",
      "value": "{{company2}}",
      "variableName": ""
    },
    {
      "command": "click",
      "condition": {
        "statement": "return '{{logged}}' !== 'yes'"
      },
      "optional": false,
      "private": false,
      "sequence": 19,
      "target": "#shipping_country",
      "value": "",
      "variableName": ""
    },
    {
      "command": "click",
      "condition": {
        "statement": "return '{{logged}}' !== 'yes'"
      },
      "optional": false,
      "private": false,
      "sequence": 20,
      "target": "#shipping_country > option[value=\"{{country}}\"]",
      "value": "",
      "variableName": ""
    },
    {
      "command": "assign",
      "condition": {
        "statement": "return '{{logged}}' !== 'yes'"
      },
      "optional": false,
      "private": false,
      "sequence": 21,
      "target": "#shipping_address_1",
      "value": "{{street3}}",
      "variableName": ""
    },
    {
      "command": "assign",
      "condition": {
        "statement": "return '{{logged}}' !== 'yes'"
      },
      "optional": false,
      "private": false,
      "sequence": 22,
      "target": "#shipping_address_2",
      "value": "{{street4}}",
      "variableName": ""
    },
    {
      "command": "assign",
      "condition": {
        "statement": "return '{{logged}}' !== 'yes'"
      },
      "optional": false,
      "private": false,
      "sequence": 23,
      "target": "#shipping_city",
      "value": "{{city}}",
      "variableName": ""
    },
    {
      "command": "click",
      "condition": {
        "statement": "return '{{logged}}' !== 'yes'"
      },
      "optional": false,
      "private": false,
      "sequence": 24,
      "target": "#shipping_state",
      "value": "",
      "variableName": ""
    },
    {
      "command": "click",
      "condition": {
        "statement": "return '{{logged}}' !== 'yes'"
      },
      "optional": false,
      "private": false,
      "sequence": 25,
      "target": "#shipping_state > option[value=\"{{state}}\"]",
      "value": "",
      "variableName": ""
    },
    {
      "command": "assign",
      "condition": {
        "statement": "return '{{logged}}' !== 'yes'"
      },
      "optional": false,
      "private": false,
      "sequence": 26,
      "target": "#shipping_postcode",
      "value": "{{zipCode}}",
      "variableName": ""
    },
    {
      "command": "execute",
      "condition": null,
      "optional": false,
      "private": false,
      "sequence": 27,
      "target": "",
      "value": "6022b74a262f437a9af8d9a3",
      "variableName": ""
    },
    {
      "command": "assign",
      "condition": null,
      "optional": false,
      "private": false,
      "sequence": 28,
      "target": "#order_comments",
      "value": "Order Note for Testing this field",
      "variableName": ""
    },
    {
      "command": "assign",
      "condition": null,
      "optional": false,
      "private": false,
      "sequence": 29,
      "target": "#purchase_repurposing",
      "value": "Test using"
    },
    {
      "command": "click",
      "condition": null,
      "optional": false,
      "private": false,
      "sequence": 30,
      "target": "#select2-how_did_you_hear_about_us-container"
    },
    {
      "command": "click",
      "condition": null,
      "optional": false,
      "private": false,
      "sequence": 31,
      "target": "//li[contains(text(), \"Google\")]"
    },
    {
      "command": "assertTextPresent",
      "condition": null,
      "optional": false,
      "private": false,
      "sequence": 32,
      "target": "td.product-name",
      "value": "{{prod_desc}}",
      "variableName": ""
    },
    {
      "command": "execute",
      "condition": {
        "statement": "return '{{product}}' === 'variable'"
      },
      "optional": false,
      "private": false,
      "sequence": 33,
      "target": "",
      "value": "6982043cf70f37399aea80e3",
      "variableName": ""
    },
    {
      "command": "assertText",
      "condition": null,
      "optional": false,
      "private": false,
      "sequence": 34,
      "target": "td.product-total > span.woocommerce-Price-amount.amount > bdi",
      "value": "{{subtotal}}",
      "variableName": ""
    },
    {
      "command": "assertText",
      "condition": null,
      "notes": "",
      "optional": false,
      "private": false,
      "sequence": 35,
      "target": [
        {
          "selector": "tr.cart-subtotal > td > .woocommerce-Price-amount.amount > bdi"
        },
        {
          "selector": "tr.cart-subtotal > td > span.woocommerce-Price-amount.amount"
        }
      ],
      "value": "{{subtotal}}",
      "variableName": ""
    },
    {
      "command": "click",
      "condition": null,
      "optional": false,
      "private": false,
      "sequence": 36,
      "target": "#shipping_method_0_local_pickup14",
      "value": "",
      "variableName": ""
    },
    {
      "command": "extractEval",
      "condition": null,
      "optional": false,
      "private": false,
      "sequence": 37,
      "target": "",
      "value": "const label = document.querySelector('#shipping_method > li:last-child > label');\nconst div = label.querySelector('div');\ndiv.remove();\nconst text = label.textContent.trim();\n\nreturn text",
      "variableName": "shippingPrice"
    },
    {
      "command": "extract",
      "condition": null,
      "optional": false,
      "private": false,
      "sequence": 38,
      "target": "tr.fee > td > .woocommerce-Price-amount.amount > bdi",
      "value": "",
      "variableName": "fee"
    },
    {
      "command": "extract",
      "condition": null,
      "optional": false,
      "private": false,
      "sequence": 39,
      "target": "tr.tax-total > td > .woocommerce-Price-amount.amount > bdi",
      "value": "",
      "variableName": "taxPrice"
    },
    {
      "command": "extract",
      "condition": null,
      "optional": false,
      "private": false,
      "sequence": 40,
      "target": "strong > .woocommerce-Price-amount.amount > bdi",
      "value": "",
      "variableName": "total"
    },
    {
      "command": "execute",
      "condition": null,
      "optional": false,
      "private": false,
      "sequence": 41,
      "target": "",
      "value": "6981fdcef70f37399ae928da",
      "variableName": ""
    },
    {
      "command": "click",
      "condition": {
        "statement": "const element = document.querySelector('#terms')\n\nreturn !element.checked"
      },
      "notes": "",
      "optional": false,
      "private": false,
      "sequence": 42,
      "target": [
        {
          "selector": "#terms"
        },
        {
          "selector": "#terms_acceptance"
        }
      ],
      "value": "",
      "variableName": ""
    }
  ],
  "testFrequency": 0,
  "testFrequencyAdvanced": [],
  "viewportSize": null,
  "_gi": {
    "testId": "698227c8f70f37399af3005d",
    "suiteId": "6981e66cf70f37399ae4ee04",
    "suiteName": "repurposedM - Common steps"
  }
}