{
  "autoRetry": null,
  "browser": null,
  "dataSource": null,
  "disableVisuals": null,
  "disallowInsecureCertificates": null,
  "failOnJavaScriptError": null,
  "filters": [],
  "finalDelay": null,
  "globalStepDelay": null,
  "httpHeaders": [],
  "importOnly": true,
  "language": null,
  "links": [],
  "maxAjaxDelay": null,
  "maxConcurrentDataRows": 1,
  "maxWaitDelay": null,
  "name": "Admin Login",
  "notifications": null,
  "publicStatusEnabled": false,
  "region": null,
  "screenshotCompareEnabled": null,
  "screenshotCompareThreshold": 0.1,
  "startUrl": "https://no-pong-au-develop.go-vip.net/wp-login.php",
  "steps": [
    {
      "command": "click",
      "condition": null,
      "optional": true,
      "private": false,
      "sequence": 0,
      "target": "a.jetpack-sso-toggle:nth-child(3)",
      "value": "",
      "variableName": ""
    },
    {
      "command": "assign",
      "condition": null,
      "optional": false,
      "private": false,
      "sequence": 1,
      "target": "#user_login",
      "value": "{{adminUser}}",
      "variableName": ""
    },
    {
      "command": "assign",
      "condition": null,
      "optional": false,
      "private": false,
      "sequence": 2,
      "target": "#user_pass",
      "value": "{{adminPass}}",
      "variableName": ""
    },
    {
      "command": "click",
      "condition": null,
      "optional": false,
      "private": false,
      "sequence": 3,
      "target": "#wp-submit",
      "value": "",
      "variableName": ""
    },
    {
      "command": "click",
      "condition": {
        "statement": "const elem = document.querySelector('#correct-admin-email')\n\nreturn !!elem"
      },
      "optional": false,
      "private": false,
      "sequence": 4,
      "target": "#correct-admin-email",
      "value": ""
    }
  ],
  "testFrequency": 0,
  "testFrequencyAdvanced": [],
  "viewportSize": null,
  "_gi": {
    "testId": "69a82b73b9fc488447ef7c9b",
    "suiteId": "69a82b73b9fc488447ef7c95",
    "suiteName": "DollarTabs - Common steps for Project"
  }
}